tile_wells/__init__.py
tile_wells/cli.py
tile_wells/tile_images.py
tile_wells-0.11.data/scripts/tile_wells
tile_wells-0.11.dist-info/DESCRIPTION.rst
tile_wells-0.11.dist-info/METADATA
tile_wells-0.11.dist-info/RECORD
tile_wells-0.11.dist-info/WHEEL
tile_wells-0.11.dist-info/metadata.json
tile_wells-0.11.dist-info/top_level.txt
