Metadata-Version: 2.0
Name: tile-wells
Version: 0.11
Summary: Place the well images of tiled fields in a layout similar to a multiwell
Requires-Dist: matplotlib
Requires-Dist: joblib
